jotunn/__init__.py
jotunn/pipeline.py
jotunn/clients/__init__.py
jotunn/clients/anyscale.py
jotunn/clients/ray.py
jotunn/components/__init__.py
jotunn/components/base.py
jotunn/components/distributed_base.py
jotunn/components/audio/__init__.py
jotunn/components/audio/segment_audio.py
jotunn/components/audio/transcription.py
jotunn/components/audio/vad.py
jotunn/components/image/__init__.py
jotunn/components/image/aesthetic.py
jotunn/components/image/blur.py
jotunn/components/image/brightness.py
jotunn/components/image/caption.py
jotunn/components/image/clarity.py
jotunn/components/image/contrast.py
jotunn/components/image/decode.py
jotunn/components/image/embedding.py
jotunn/components/image/entropy.py
jotunn/components/image/file_size.py
jotunn/components/image/image_hashing.py
jotunn/components/image/intensive_text.py
jotunn/components/image/nsfw.py
jotunn/components/image/resize.py
jotunn/components/image/resolution.py
jotunn/components/image/rotation.py
jotunn/components/image/saturation.py
jotunn/components/image/watermark.py
jotunn/components/similarity/similarity.py
jotunn/components/text/__init__.py
jotunn/components/text/alphanumeric.py
jotunn/components/text/digit.py
jotunn/components/text/embedding.py
jotunn/components/text/fineweb_edu.py
jotunn/components/text/long_words.py
jotunn/components/text/refusals.py
jotunn/components/text/text_length.py
jotunn/components/text/token_length.py
jotunn/components/video/__init__.py
jotunn/components/video/cotracker.py
jotunn/components/video/frame_extractor.py
jotunn/components/video/optical_flow.py
jotunn/components/video/video_duration.py
jotunn/components/video/video_segmentation.py
jotunn/components/video/video_stats.py
jotunn/models/__init__.py
jotunn/models/laion.py
jotunn/models/owl_watermark.py
jotunn-0.1.260.dist-info/licenses/LICENSE
utils/validate_files.py
jotunn-0.1.260.dist-info/METADATA
jotunn-0.1.260.dist-info/WHEEL
jotunn-0.1.260.dist-info/top_level.txt
jotunn-0.1.260.dist-info/RECORD
