Metadata-Version: 2.4
Name: jotunn
Version: 0.1.260
Summary: A petabyte scale data processing framework for AI models using Ray.
Author-email: Teraflop AI <enrico@teraflop.ai>
Classifier: Typing :: Typed
Classifier: Intended Audience :: Developers
Classifier: Programming Language :: Python :: 3.10
Classifier: Programming Language :: Python :: 3.11
Classifier: Programming Language :: Python :: 3.12
Classifier: Programming Language :: Python :: 3.13
Classifier: Topic :: Software Development :: Libraries :: Python Modules
Requires-Python: >=3.10
License-File: LICENSE
Requires-Dist: daft
Requires-Dist: google-re2>=1.1.20250805
Requires-Dist: loguru>=0.7.3
Requires-Dist: matplotlib>=3.10.6
Requires-Dist: memray>=1.18.0
Requires-Dist: open-clip-torch>=3.2.0
Requires-Dist: pysimdjson>=7.0.2
Requires-Dist: rapidfuzz>=3.14.1
Requires-Dist: ray[data]>=2.47.1
Requires-Dist: transformers>=4.53.3
Requires-Dist: usearch>=2.21.0
Requires-Dist: xxhash>=3.5.0
Provides-Extra: text
Requires-Dist: trafilatura>=2.0.0; extra == "text"
Requires-Dist: chonkie>=1.1.0; extra == "text"
Requires-Dist: sentence-transformers>=5.0.0; extra == "text"
Requires-Dist: vllm>=0.9.2; extra == "text"
Provides-Extra: audio
Requires-Dist: librosa>=0.11.0; extra == "audio"
Requires-Dist: silero-vad>=5.1.2; extra == "audio"
Requires-Dist: soundfile>=0.13.1; extra == "audio"
Provides-Extra: video
Requires-Dist: av>=15.1.0; extra == "video"
Requires-Dist: scenedetect>=0.6.6; extra == "video"
Requires-Dist: video-reader-rs>=0.2.10; extra == "video"
Provides-Extra: image
Requires-Dist: easyocr>=1.7.2; extra == "image"
Requires-Dist: exifread>=3.5.1; extra == "image"
Requires-Dist: imagehash>=4.3.2; extra == "image"
Requires-Dist: opencv-python>=4.12.0.88; extra == "image"
Requires-Dist: pillow-simd>=9.5.0.post2; extra == "image"
Requires-Dist: scikit-image>=0.25.2; extra == "image"
Requires-Dist: simple-aesthetics-predictor>=0.1.2; extra == "image"
Requires-Dist: vllm>=0.9.2; extra == "image"
Provides-Extra: anyscale
Requires-Dist: anyscale>=0.26.58; extra == "anyscale"
Provides-Extra: all
Requires-Dist: jotunn[anyscale,audio,image,text,video]; extra == "all"
Dynamic: license-file
